slime_core/__init__.py
slime_core/_archived/__init__.py
slime_core/context/__init__.py
slime_core/context/compile.py
slime_core/handlers/__init__.py
slime_core/handlers/wrapper.py
slime_core/hooks/__init__.py
slime_core/hooks/build.py
slime_core/hooks/launch.py
slime_core/hooks/plugin.py
slime_core/logging/__init__.py
slime_core/logging/logger.py
slime_core/utils/__init__.py
slime_core/utils/base.py
slime_core/utils/common.py
slime_core/utils/decorator.py
slime_core/utils/exception.py
slime_core/utils/launch.py
slime_core/utils/metabase.py
slime_core/utils/metaclass.py
slime_core/utils/registry.py
slime_core/utils/store.py
slime_core/utils/typing.py
slime_core/utils/abcs/__init__.py
slime_core/utils/abcs/base.py
slime_core/utils/cli/__init__.py
slime_core-0.0.1.dist-info/LICENSE
slime_core-0.0.1.dist-info/METADATA
slime_core-0.0.1.dist-info/WHEEL
slime_core-0.0.1.dist-info/top_level.txt
slime_core-0.0.1.dist-info/RECORD
