Metadata-Version: 2.1
Name: slime-core
Version: 0.0.1
Summary: slime_core
Home-page: https://github.com/SlimeAI/slime_core
Author: SlimeAI
Author-email: liuzikang0625@gmail.com
License: MIT License
License-File: LICENSE
